ezyml/__init__.py
ezyml/cli.py
ezyml/core.py
ezyml/compiler/__init__.py
ezyml/compiler/compile.py
ezyml/deploy/__init__.py
ezyml/deploy/docker.py
ezyml/deploy/fastapi.py
ezyml/deploy/k8s.py
ezyml/deploy/openapi.py
ezyml/deploy/streamlit.py
ezyml/devx/__init___.py
ezyml/devx/doctor.py
ezyml/devx/init.py
ezyml/eda/__init__.py
ezyml/eda/auto_eda.py
ezyml/evaluation/__init__.py
ezyml/evaluation/evaluator.py
ezyml/evaluation/metrics.py
ezyml/evaluation/plots.py
ezyml/explain/__init__.py
ezyml/explain/learner.py
ezyml/monitoring/__init__.py
ezyml/monitoring/drift.py
ezyml/monitoring/fingerprint.py
ezyml/pipeline/__init__.py
ezyml/pipeline/loader.py
ezyml/pipeline/visualize.py
ezyml/training/__init__.py
ezyml/training/tuner.py
ezyml-2.dist-info/licenses/LICENSE
ezyml-2.dist-info/METADATA
ezyml-2.dist-info/WHEEL
ezyml-2.dist-info/entry_points.txt
ezyml-2.dist-info/top_level.txt
ezyml-2.dist-info/RECORD
