Metadata-Version: 2.4
Name: ezyml
Version: 2
Summary: From dataset to production ML system — in one command.
Home-page: https://github.com/Rktim/ezyml
Author: Raktim Kalita
Author-email: Raktim Kalita <raktimkalita.ai@gmail.com>
License: MIT
Keywords: machine-learning,ml,mlops,automation,scikit-learn,deployment,fastapi,streamlit,kubernetes
Classifier: Development Status :: 4 - Beta
Classifier: Intended Audience :: Developers
Classifier: Intended Audience :: Science/Research
Classifier: License :: OSI Approved :: MIT License
Classifier: Programming Language :: Python :: 3
Classifier: Programming Language :: Python :: 3.9
Classifier: Programming Language :: Python :: 3.10
Classifier: Programming Language :: Python :: 3.11
Classifier: Programming Language :: Python :: 3.12
Classifier: Topic :: Scientific/Engineering :: Artificial Intelligence
Requires-Python: >=3.7
License-File: LICENSE
Requires-Dist: numpy>=1.23
Requires-Dist: pandas>=1.5
Requires-Dist: scikit-learn>=1.3
Requires-Dist: scipy>=1.9
Requires-Dist: xgboost>=1.7
Requires-Dist: pyyaml>=6.0
Provides-Extra: demo
Requires-Dist: streamlit>=1.30; extra == "demo"
Provides-Extra: api
Requires-Dist: fastapi>=0.110; extra == "api"
Requires-Dist: uvicorn>=0.25; extra == "api"
Provides-Extra: deploy
Requires-Dist: docker; extra == "deploy"
Requires-Dist: kubernetes; extra == "deploy"
Provides-Extra: dev
Requires-Dist: pytest; extra == "dev"
Requires-Dist: black; extra == "dev"
Requires-Dist: ruff; extra == "dev"
Requires-Dist: mypy; extra == "dev"
Requires-Dist: twine; extra == "dev"
Provides-Extra: all
Requires-Dist: streamlit>=1.30; extra == "all"
Requires-Dist: fastapi>=0.110; extra == "all"
Requires-Dist: uvicorn>=0.25; extra == "all"
Requires-Dist: docker; extra == "all"
Requires-Dist: kubernetes; extra == "all"
Dynamic: author
Dynamic: home-page
Dynamic: license-file
Dynamic: requires-python
